datasette_expose_env/__init__.py
datasette_expose_env-0.2.dist-info/LICENSE
datasette_expose_env-0.2.dist-info/METADATA
datasette_expose_env-0.2.dist-info/WHEEL
datasette_expose_env-0.2.dist-info/entry_points.txt
datasette_expose_env-0.2.dist-info/top_level.txt
datasette_expose_env-0.2.dist-info/RECORD
