Metadata-Version: 2.1
Name: datasette-expose-env
Version: 0.2
Summary: Datasette plugin to expose selected environment variables at /-/env for debugging
Home-page: https://github.com/simonw/datasette-expose-env
Author: Simon Willison
License: Apache License, Version 2.0
Project-URL: Issues, https://github.com/simonw/datasette-expose-env/issues
Project-URL: CI, https://github.com/simonw/datasette-expose-env/actions
Project-URL: Changelog, https://github.com/simonw/datasette-expose-env/releases
Classifier: Framework :: Datasette
Classifier: License :: OSI Approved :: Apache Software License
Requires-Python: >=3.8
License-File: LICENSE
Requires-Dist: datasette
Provides-Extra: test
Requires-Dist: pytest ; extra == 'test'
Requires-Dist: pytest-asyncio ; extra == 'test'
Requires-Dist: datasette-test ; extra == 'test'
